ood/__init__.py
ood/exceptions.py
ood/ordereddictionary.py
ood/selectors.py
ood-1.0.9.dist-info/METADATA
ood-1.0.9.dist-info/WHEEL
ood-1.0.9.dist-info/top_level.txt
ood-1.0.9.dist-info/RECORD
