Metadata-Version: 2.1
Name: ood
Version: 1.0.9
Summary: Observing Ordered Dictionary: multidicts accessed by position/name and which watch child changes
Requires-Python: >=3.9
Provides-Extra: dev
Requires-Dist: pytest ; extra == 'dev'
